langchain_sandbox_zp/__init__.py
langchain_sandbox_zp/py.typed
langchain_sandbox_zp/pyodide.py
langchain_sandbox_zp-0.0.8.dist-info/METADATA
langchain_sandbox_zp-0.0.8.dist-info/WHEEL
langchain_sandbox_zp-0.0.8.dist-info/RECORD
